{"users":[{"user_id":"8b344a44-287f-46a6-879b-b9491d5adb93","deposit_accounts":[],"savings_accounts":[{"account_id":"3ad7b668-e6fb-4a56-8fea-8137926cc71a","physical_cards":[],"virtual_cards":[],"top_up_operations":[],"purchase_operations":[],"transfer_operations":[],"cash_withdrawal_operations":[]}],"debit_card_accounts":[{"account_id":"e6ca785a-7c38-4d1c-be2d-e83489a67881","physical_cards":[],"virtual_cards":[],"top_up_operations":[],"purchase_operations":[],"transfer_operations":[],"cash_withdrawal_operations":[]}],"credit_card_accounts":[]},{"user_id":"346dc659-5922-492c-857e-6d7c2330347a","deposit_accounts":[],"savings_accounts":[{"account_id":"8598c103-9022-4faf-a134-d9d689c038fe","physical_cards":[],"virtual_cards":[],"top_up_operations":[],"purchase_operations":[],"transfer_operations":[],"cash_withdrawal_operations":[]}],"debit_card_accounts":[{"account_id":"cda82a4e-6a4d-4c32-841a-66232ce4bb5f","physical_cards":[],"virtual_cards":[],"top_up_operations":[],"purchase_operations":[],"transfer_operations":[],"cash_withdrawal_operations":[]}],"credit_card_accounts":[]},{"user_id":"b2e76d8d-a22e-4a1a-aff2-b0c433bb145c","deposit_accounts":[],"savings_accounts":[{"account_id":"ceb32144-30ea-4fc8-86f8-086e02470c91","physical_cards":[],"virtual_cards":[],"top_up_operations":[],"purchase_operations":[],"transfer_operations":[],"cash_withdrawal_operations":[]}],"debit_card_accounts":[{"account_id":"10718720-5ad4-4324-acc9-bae56e8e7d24","physical_cards":[],"virtual_cards":[],"top_up_operations":[],"purchase_operations":[],"transfer_operations":[],"cash_withdrawal_operations":[]}],"credit_card_accounts":[]},{"user_id":"e3e05d8a-f7ed-4b60-82d1-594876dc810b","deposit_accounts":[],"savings_accounts":[{"account_id":"348b6b02-c86f-4126-a7de-26a1ca0fae90","physical_cards":[],"virtual_cards":[],"top_up_operations":[],"purchase_operations":[],"transfer_operations":[],"cash_withdrawal_operations":[]}],"debit_card_accounts":[{"account_id":"5208d41e-7b8b-44a1-b805-2606750decea","physical_cards":[],"virtual_cards":[],"top_up_operations":[],"purchase_operations":[],"transfer_operations":[],"cash_withdrawal_operations":[]}],"credit_card_accounts":[]},{"user_id":"d3d89005-4529-47c4-b15c-b56b51fa2ef2","deposit_accounts":[],"savings_accounts":[{"account_id":"4ece021f-33e2-41aa-a406-a17cc9361232","physical_cards":[],"virtual_cards":[],"top_up_operations":[],"purchase_operations":[],"transfer_operations":[],"cash_withdrawal_operations":[]}],"debit_card_accounts":[{"account_id":"c2900ef5-7a36-4f53-8e85-4f0e720b5857","physical_cards":[],"virtual_cards":[],"top_up_operations":[],"purchase_operations":[],"transfer_operations":[],"cash_withdrawal_operations":[]}],"credit_card_accounts":[]},{"user_id":"3e75a8da-5c65-4003-9420-d4e6eb6d0842","deposit_accounts":[],"savings_accounts":[{"account_id":"198ded48-1930-4cdf-8555-9379ea081304","physical_cards":[],"virtual_cards":[],"top_up_operations":[],"purchase_operations":[],"transfer_operations":[],"cash_withdrawal_operations":[]}],"debit_card_accounts":[{"account_id":"8dc1e37e-b33b-444f-90a2-e0a00f7c1a5e","physical_cards":[],"virtual_cards":[],"top_up_operations":[],"purchase_operations":[],"transfer_operations":[],"cash_withdrawal_operations":[]}],"credit_card_accounts":[]},{"user_id":"bf3bbf73-de92-42d0-b961-33bba8749b11","deposit_accounts":[],"savings_accounts":[{"account_id":"cb2ac929-c136-4e8d-8444-17efdb8d85de","physical_cards":[],"virtual_cards":[],"top_up_operations":[],"purchase_operations":[],"transfer_operations":[],"cash_withdrawal_operations":[]}],"debit_card_accounts":[{"account_id":"bd45d83b-4e97-4dc5-ade4-4f73fb6bcb16","physical_cards":[],"virtual_cards":[],"top_up_operations":[],"purchase_operations":[],"transfer_operations":[],"cash_withdrawal_operations":[]}],"credit_card_accounts":[]},{"user_id":"59cb25bc-9eb0-4485-a8c1-0f49f7095012","deposit_accounts":[],"savings_accounts":[{"account_id":"ecd1fe02-0146-43ad-bca1-2048b6c3469d","physical_cards":[],"virtual_cards":[],"top_up_operations":[],"purchase_operations":[],"transfer_operations":[],"cash_withdrawal_operations":[]}],"debit_card_accounts":[{"account_id":"75c1e7ee-615e-43e7-866c-5ebb3160e75c","physical_cards":[],"virtual_cards":[],"top_up_operations":[],"purchase_operations":[],"transfer_operations":[],"cash_withdrawal_operations":[]}],"credit_card_accounts":[]},{"user_id":"1eb403b6-81e4-4729-85c3-9fcc1f170c0a","deposit_accounts":[],"savings_accounts":[{"account_id":"84314cdb-4453-462f-84c8-d0fff18712d4","physical_cards":[],"virtual_cards":[],"top_up_operations":[],"purchase_operations":[],"transfer_operations":[],"cash_withdrawal_operations":[]}],"debit_card_accounts":[{"account_id":"64118d93-82da-4a89-b113-03b54002e306","physical_cards":[],"virtual_cards":[],"top_up_operations":[],"purchase_operations":[],"transfer_operations":[],"cash_withdrawal_operations":[]}],"credit_card_accounts":[]},{"user_id":"b9dd01aa-b560-4abc-92c3-282e3142f075","deposit_accounts":[],"savings_accounts":[{"account_id":"a028327e-5f2d-45a0-83a5-437593edaa02","physical_cards":[],"virtual_cards":[],"top_up_operations":[],"purchase_operations":[],"transfer_operations":[],"cash_withdrawal_operations":[]}],"debit_card_accounts":[{"account_id":"8621e447-9fcc-413c-a5bb-2385a6c45378","physical_cards":[],"virtual_cards":[],"top_up_operations":[],"purchase_operations":[],"transfer_operations":[],"cash_withdrawal_operations":[]}],"credit_card_accounts":[]},{"user_id":"8010ef49-ad4e-41db-80cf-4e5ac05f83fe","deposit_accounts":[],"savings_accounts":[{"account_id":"7c644406-6833-4317-94a1-30d93b2d004a","physical_cards":[],"virtual_cards":[],"top_up_operations":[],"purchase_operations":[],"transfer_operations":[],"cash_withdrawal_operations":[]}],"debit_card_accounts":[{"account_id":"dbab7894-0849-4a6e-ba69-b180eae0e4d3","physical_cards":[],"virtual_cards":[],"top_up_operations":[],"purchase_operations":[],"transfer_operations":[],"cash_withdrawal_operations":[]}],"credit_card_accounts":[]},{"user_id":"778c391d-8830-44e3-8a24-50223eb124ab","deposit_accounts":[],"savings_accounts":[{"account_id":"9caee499-d2eb-4fd4-be80-bea4ebc6ff74","physical_cards":[],"virtual_cards":[],"top_up_operations":[],"purchase_operations":[],"transfer_operations":[],"cash_withdrawal_operations":[]}],"debit_card_accounts":[{"account_id":"c31fa7c2-917c-4e7b-a197-212c3ca46c7a","physical_cards":[],"virtual_cards":[],"top_up_operations":[],"purchase_operations":[],"transfer_operations":[],"cash_withdrawal_operations":[]}],"credit_card_accounts":[]},{"user_id":"001bef37-8e6d-4029-9e3a-f6160dcd0d99","deposit_accounts":[],"savings_accounts":[{"account_id":"6a7466fc-0367-4c0f-be03-fa4b4d3fda33","physical_cards":[],"virtual_cards":[],"top_up_operations":[],"purchase_operations":[],"transfer_operations":[],"cash_withdrawal_operations":[]}],"debit_card_accounts":[{"account_id":"7737ef27-dbb1-4a34-862e-40c1e721cc88","physical_cards":[],"virtual_cards":[],"top_up_operations":[],"purchase_operations":[],"transfer_operations":[],"cash_withdrawal_operations":[]}],"credit_card_accounts":[]},{"user_id":"0538c391-6876-4204-b15f-d95406c7d151","deposit_accounts":[],"savings_accounts":[{"account_id":"dcff00e4-096e-4a9c-a830-3a6342a25475","physical_cards":[],"virtual_cards":[],"top_up_operations":[],"purchase_operations":[],"transfer_operations":[],"cash_withdrawal_operations":[]}],"debit_card_accounts":[{"account_id":"03e78476-24e7-456e-a7e8-f5026417b889","physical_cards":[],"virtual_cards":[],"top_up_operations":[],"purchase_operations":[],"transfer_operations":[],"cash_withdrawal_operations":[]}],"credit_card_accounts":[]},{"user_id":"407f9763-28a8-4fc4-afff-a7d5006a15d1","deposit_accounts":[],"savings_accounts":[{"account_id":"1bdfda79-3402-4c29-8b92-4badfabe7e26","physical_cards":[],"virtual_cards":[],"top_up_operations":[],"purchase_operations":[],"transfer_operations":[],"cash_withdrawal_operations":[]}],"debit_card_accounts":[{"account_id":"cdb4c177-ded2-4b1f-8cc5-484a709e74a4","physical_cards":[],"virtual_cards":[],"top_up_operations":[],"purchase_operations":[],"transfer_operations":[],"cash_withdrawal_operations":[]}],"credit_card_accounts":[]},{"user_id":"4cd46995-44b4-4f5b-b0c3-4a4df5280a4b","deposit_accounts":[],"savings_accounts":[{"account_id":"91e82ab0-bc77-48bf-a47f-e12f0973dfce","physical_cards":[],"virtual_cards":[],"top_up_operations":[],"purchase_operations":[],"transfer_operations":[],"cash_withdrawal_operations":[]}],"debit_card_accounts":[{"account_id":"4f3c3434-0a36-4bee-a53d-5375f1e3927b","physical_cards":[],"virtual_cards":[],"top_up_operations":[],"purchase_operations":[],"transfer_operations":[],"cash_withdrawal_operations":[]}],"credit_card_accounts":[]},{"user_id":"ad177f07-fddc-417c-b9a5-ff9df57139a7","deposit_accounts":[],"savings_accounts":[{"account_id":"6f9c4cae-57ff-4121-be74-3f9ea187ffa2","physical_cards":[],"virtual_cards":[],"top_up_operations":[],"purchase_operations":[],"transfer_operations":[],"cash_withdrawal_operations":[]}],"debit_card_accounts":[{"account_id":"68f840a9-131f-4fd9-af7d-9381a20107e8","physical_cards":[],"virtual_cards":[],"top_up_operations":[],"purchase_operations":[],"transfer_operations":[],"cash_withdrawal_operations":[]}],"credit_card_accounts":[]},{"user_id":"8f37bb22-f7a2-4b8d-8a8c-27f1d5babc31","deposit_accounts":[],"savings_accounts":[{"account_id":"baf3b616-271a-4ca0-b32a-d67dfeac323c","physical_cards":[],"virtual_cards":[],"top_up_operations":[],"purchase_operations":[],"transfer_operations":[],"cash_withdrawal_operations":[]}],"debit_card_accounts":[{"account_id":"55e40351-15f0-414a-a3d9-0f365a593454","physical_cards":[],"virtual_cards":[],"top_up_operations":[],"purchase_operations":[],"transfer_operations":[],"cash_withdrawal_operations":[]}],"credit_card_accounts":[]},{"user_id":"6a3d8fd9-93b2-4b06-a1a6-1c605a8216ff","deposit_accounts":[],"savings_accounts":[{"account_id":"1eff24ed-eecc-4a07-bc6f-3d29f6e21a6a","physical_cards":[],"virtual_cards":[],"top_up_operations":[],"purchase_operations":[],"transfer_operations":[],"cash_withdrawal_operations":[]}],"debit_card_accounts":[{"account_id":"27c15b53-3530-45b2-9cc7-36a5037d0985","physical_cards":[],"virtual_cards":[],"top_up_operations":[],"purchase_operations":[],"transfer_operations":[],"cash_withdrawal_operations":[]}],"credit_card_accounts":[]},{"user_id":"674c8a36-89b6-4925-be62-e932ab801883","deposit_accounts":[],"savings_accounts":[{"account_id":"60a65aa4-d228-414f-b1b5-3751e264ac7c","physical_cards":[],"virtual_cards":[],"top_up_operations":[],"purchase_operations":[],"transfer_operations":[],"cash_withdrawal_operations":[]}],"debit_card_accounts":[{"account_id":"6b4bd0b3-9e85-4a2a-b69a-863879f4b124","physical_cards":[],"virtual_cards":[],"top_up_operations":[],"purchase_operations":[],"transfer_operations":[],"cash_withdrawal_operations":[]}],"credit_card_accounts":[]},{"user_id":"bff11c78-4aea-4f59-ae70-20548a0781ba","deposit_accounts":[],"savings_accounts":[{"account_id":"8d9f57b1-d193-4c8c-b752-c839d80a1ecc","physical_cards":[],"virtual_cards":[],"top_up_operations":[],"purchase_operations":[],"transfer_operations":[],"cash_withdrawal_operations":[]}],"debit_card_accounts":[{"account_id":"f0d2b44c-358c-45b9-b36d-3865aee4f2d4","physical_cards":[],"virtual_cards":[],"top_up_operations":[],"purchase_operations":[],"transfer_operations":[],"cash_withdrawal_operations":[]}],"credit_card_accounts":[]},{"user_id":"31abe05f-f825-4180-9608-872e3f36a44a","deposit_accounts":[],"savings_accounts":[{"account_id":"ddb04ca1-2974-4c9b-a021-3d9971907a8a","physical_cards":[],"virtual_cards":[],"top_up_operations":[],"purchase_operations":[],"transfer_operations":[],"cash_withdrawal_operations":[]}],"debit_card_accounts":[{"account_id":"d631ceb1-f54c-4e39-bf86-d91eff18ab9a","physical_cards":[],"virtual_cards":[],"top_up_operations":[],"purchase_operations":[],"transfer_operations":[],"cash_withdrawal_operations":[]}],"credit_card_accounts":[]},{"user_id":"adb870f6-a344-4abc-88f4-6d37afaefcd5","deposit_accounts":[],"savings_accounts":[{"account_id":"7b854cae-8995-4f57-9ea9-54f15b4e8713","physical_cards":[],"virtual_cards":[],"top_up_operations":[],"purchase_operations":[],"transfer_operations":[],"cash_withdrawal_operations":[]}],"debit_card_accounts":[{"account_id":"60c80aa4-287a-465e-9a91-fa956d8d561d","physical_cards":[],"virtual_cards":[],"top_up_operations":[],"purchase_operations":[],"transfer_operations":[],"cash_withdrawal_operations":[]}],"credit_card_accounts":[]},{"user_id":"4fc05f2d-e07f-4cb4-93a7-7544cbd1d390","deposit_accounts":[],"savings_accounts":[{"account_id":"02f40dca-6333-4519-80db-fa5d2529fd44","physical_cards":[],"virtual_cards":[],"top_up_operations":[],"purchase_operations":[],"transfer_operations":[],"cash_withdrawal_operations":[]}],"debit_card_accounts":[{"account_id":"a16ccf00-9d9f-4c13-87d4-b54f531be019","physical_cards":[],"virtual_cards":[],"top_up_operations":[],"purchase_operations":[],"transfer_operations":[],"cash_withdrawal_operations":[]}],"credit_card_accounts":[]},{"user_id":"0cdb156d-203a-44f4-a275-8b0af1f0ba43","deposit_accounts":[],"savings_accounts":[{"account_id":"78ec5f78-ac34-48cc-acbb-c3428d986f60","physical_cards":[],"virtual_cards":[],"top_up_operations":[],"purchase_operations":[],"transfer_operations":[],"cash_withdrawal_operations":[]}],"debit_card_accounts":[{"account_id":"b7f3016b-d4bf-482d-a030-43cb8eda6088","physical_cards":[],"virtual_cards":[],"top_up_operations":[],"purchase_operations":[],"transfer_operations":[],"cash_withdrawal_operations":[]}],"credit_card_accounts":[]},{"user_id":"61429035-ef7b-4a33-8071-f450b80d2bd6","deposit_accounts":[],"savings_accounts":[{"account_id":"4d648351-7c7a-40fe-8950-47354011ad67","physical_cards":[],"virtual_cards":[],"top_up_operations":[],"purchase_operations":[],"transfer_operations":[],"cash_withdrawal_operations":[]}],"debit_card_accounts":[{"account_id":"f379ef23-f37d-492f-bbf4-737123f5e9c3","physical_cards":[],"virtual_cards":[],"top_up_operations":[],"purchase_operations":[],"transfer_operations":[],"cash_withdrawal_operations":[]}],"credit_card_accounts":[]},{"user_id":"6a0dbf1c-516b-4171-a7bc-51143f149246","deposit_accounts":[],"savings_accounts":[{"account_id":"6e713c2c-b6e4-48fb-82bf-e3b6f03e61fb","physical_cards":[],"virtual_cards":[],"top_up_operations":[],"purchase_operations":[],"transfer_operations":[],"cash_withdrawal_operations":[]}],"debit_card_accounts":[{"account_id":"05dbf631-be75-4a9b-9668-e1335818892a","physical_cards":[],"virtual_cards":[],"top_up_operations":[],"purchase_operations":[],"transfer_operations":[],"cash_withdrawal_operations":[]}],"credit_card_accounts":[]},{"user_id":"bec4f0da-5d73-40f6-bb7c-be7ccda38a4f","deposit_accounts":[],"savings_accounts":[{"account_id":"3305e1ae-d672-4d5e-bda1-ca388178829c","physical_cards":[],"virtual_cards":[],"top_up_operations":[],"purchase_operations":[],"transfer_operations":[],"cash_withdrawal_operations":[]}],"debit_card_accounts":[{"account_id":"4888952f-3e9e-4574-a1c7-abd08aa5abdc","physical_cards":[],"virtual_cards":[],"top_up_operations":[],"purchase_operations":[],"transfer_operations":[],"cash_withdrawal_operations":[]}],"credit_card_accounts":[]},{"user_id":"f20339a4-d4ce-4a4f-9cb7-72038b96704b","deposit_accounts":[],"savings_accounts":[{"account_id":"8d5ce866-f4e5-4764-b918-3f0996d8229d","physical_cards":[],"virtual_cards":[],"top_up_operations":[],"purchase_operations":[],"transfer_operations":[],"cash_withdrawal_operations":[]}],"debit_card_accounts":[{"account_id":"e275a746-f970-456b-a8af-bfb64db225e6","physical_cards":[],"virtual_cards":[],"top_up_operations":[],"purchase_operations":[],"transfer_operations":[],"cash_withdrawal_operations":[]}],"credit_card_accounts":[]},{"user_id":"e94c2d8c-4ad2-48dd-bebb-c1d079ea1415","deposit_accounts":[],"savings_accounts":[{"account_id":"dde9760d-ab6e-4597-9edb-a6ae9593dfaf","physical_cards":[],"virtual_cards":[],"top_up_operations":[],"purchase_operations":[],"transfer_operations":[],"cash_withdrawal_operations":[]}],"debit_card_accounts":[{"account_id":"8960b9b4-fb24-4837-8639-9a4f67cfafbb","physical_cards":[],"virtual_cards":[],"top_up_operations":[],"purchase_operations":[],"transfer_operations":[],"cash_withdrawal_operations":[]}],"credit_card_accounts":[]},{"user_id":"c94c16a0-f3a5-418e-a431-2315adea5d9b","deposit_accounts":[],"savings_accounts":[{"account_id":"ba98a774-e806-4037-aa5c-679bdcb30014","physical_cards":[],"virtual_cards":[],"top_up_operations":[],"purchase_operations":[],"transfer_operations":[],"cash_withdrawal_operations":[]}],"debit_card_accounts":[{"account_id":"e8a7ff2d-0e15-43a0-960e-44dee5749b99","physical_cards":[],"virtual_cards":[],"top_up_operations":[],"purchase_operations":[],"transfer_operations":[],"cash_withdrawal_operations":[]}],"credit_card_accounts":[]},{"user_id":"e81d0da3-7afc-4fd0-b64e-01e443dfbd3e","deposit_accounts":[],"savings_accounts":[{"account_id":"5a2ff4c4-1f54-4f99-98f3-092d8cdeb00b","physical_cards":[],"virtual_cards":[],"top_up_operations":[],"purchase_operations":[],"transfer_operations":[],"cash_withdrawal_operations":[]}],"debit_card_accounts":[{"account_id":"41145c69-6f8c-437a-a27d-2bc0d5285bd3","physical_cards":[],"virtual_cards":[],"top_up_operations":[],"purchase_operations":[],"transfer_operations":[],"cash_withdrawal_operations":[]}],"credit_card_accounts":[]},{"user_id":"ff8ea08c-59da-40db-9ceb-e0a08006f883","deposit_accounts":[],"savings_accounts":[{"account_id":"c92b72f8-dc8f-497b-8941-8bcc86abbe60","physical_cards":[],"virtual_cards":[],"top_up_operations":[],"purchase_operations":[],"transfer_operations":[],"cash_withdrawal_operations":[]}],"debit_card_accounts":[{"account_id":"b12ac298-7321-4b24-ba24-898295a8c123","physical_cards":[],"virtual_cards":[],"top_up_operations":[],"purchase_operations":[],"transfer_operations":[],"cash_withdrawal_operations":[]}],"credit_card_accounts":[]},{"user_id":"00e84227-44a7-45bd-95cd-c5a810d27a68","deposit_accounts":[],"savings_accounts":[{"account_id":"f9708222-c942-4758-b111-3f9b9f174457","physical_cards":[],"virtual_cards":[],"top_up_operations":[],"purchase_operations":[],"transfer_operations":[],"cash_withdrawal_operations":[]}],"debit_card_accounts":[{"account_id":"517a945d-fc34-4edf-b145-2d619d230599","physical_cards":[],"virtual_cards":[],"top_up_operations":[],"purchase_operations":[],"transfer_operations":[],"cash_withdrawal_operations":[]}],"credit_card_accounts":[]},{"user_id":"4ffea5f4-8b97-4b92-9473-a347f4cf3485","deposit_accounts":[],"savings_accounts":[{"account_id":"8292949f-a939-4496-bd48-bf08fb665704","physical_cards":[],"virtual_cards":[],"top_up_operations":[],"purchase_operations":[],"transfer_operations":[],"cash_withdrawal_operations":[]}],"debit_card_accounts":[{"account_id":"8f3239a9-2b79-4940-aea9-84d4f7588fa2","physical_cards":[],"virtual_cards":[],"top_up_operations":[],"purchase_operations":[],"transfer_operations":[],"cash_withdrawal_operations":[]}],"credit_card_accounts":[]},{"user_id":"7ea7e714-ff04-44f0-9a95-04915208a17d","deposit_accounts":[],"savings_accounts":[{"account_id":"a0ed4e56-c59b-4893-b506-02b0f363f3a3","physical_cards":[],"virtual_cards":[],"top_up_operations":[],"purchase_operations":[],"transfer_operations":[],"cash_withdrawal_operations":[]}],"debit_card_accounts":[{"account_id":"52c48753-f259-477b-b6c4-13cdeab3eba8","physical_cards":[],"virtual_cards":[],"top_up_operations":[],"purchase_operations":[],"transfer_operations":[],"cash_withdrawal_operations":[]}],"credit_card_accounts":[]},{"user_id":"1378d1bd-270e-4ef8-98bf-3b10664f7a11","deposit_accounts":[],"savings_accounts":[{"account_id":"70a36cd1-19a2-4b38-826c-559881efb70c","physical_cards":[],"virtual_cards":[],"top_up_operations":[],"purchase_operations":[],"transfer_operations":[],"cash_withdrawal_operations":[]}],"debit_card_accounts":[{"account_id":"44303d8d-b81e-44f9-a2b2-59d6de0e90d2","physical_cards":[],"virtual_cards":[],"top_up_operations":[],"purchase_operations":[],"transfer_operations":[],"cash_withdrawal_operations":[]}],"credit_card_accounts":[]},{"user_id":"fd62e4ea-fd37-4d18-b3a1-e5aae54b8902","deposit_accounts":[],"savings_accounts":[{"account_id":"8a3a04c9-6c9e-48b9-be80-b030210be31c","physical_cards":[],"virtual_cards":[],"top_up_operations":[],"purchase_operations":[],"transfer_operations":[],"cash_withdrawal_operations":[]}],"debit_card_accounts":[{"account_id":"89b18386-5c7f-4111-955a-0276fda51206","physical_cards":[],"virtual_cards":[],"top_up_operations":[],"purchase_operations":[],"transfer_operations":[],"cash_withdrawal_operations":[]}],"credit_card_accounts":[]},{"user_id":"68c62541-bf17-4f23-936f-3a3795357efa","deposit_accounts":[],"savings_accounts":[{"account_id":"090da8c0-05ea-4e4f-bc98-6eeea051a549","physical_cards":[],"virtual_cards":[],"top_up_operations":[],"purchase_operations":[],"transfer_operations":[],"cash_withdrawal_operations":[]}],"debit_card_accounts":[{"account_id":"a12e461f-7726-46ac-8d60-bd55babb6106","physical_cards":[],"virtual_cards":[],"top_up_operations":[],"purchase_operations":[],"transfer_operations":[],"cash_withdrawal_operations":[]}],"credit_card_accounts":[]},{"user_id":"6d83cfae-7eef-4793-aa6b-bee0268e94c2","deposit_accounts":[],"savings_accounts":[{"account_id":"438cc338-a5b6-4912-850f-92a6557c2a21","physical_cards":[],"virtual_cards":[],"top_up_operations":[],"purchase_operations":[],"transfer_operations":[],"cash_withdrawal_operations":[]}],"debit_card_accounts":[{"account_id":"2498d4b7-9193-49f6-ace3-b74c05e7fa1b","physical_cards":[],"virtual_cards":[],"top_up_operations":[],"purchase_operations":[],"transfer_operations":[],"cash_withdrawal_operations":[]}],"credit_card_accounts":[]},{"user_id":"45cf5309-6ecf-46fb-b4e5-d9a762b410a8","deposit_accounts":[],"savings_accounts":[{"account_id":"b208f4d1-83cf-4500-816c-b13f9941d321","physical_cards":[],"virtual_cards":[],"top_up_operations":[],"purchase_operations":[],"transfer_operations":[],"cash_withdrawal_operations":[]}],"debit_card_accounts":[{"account_id":"4c41d195-387e-485e-9828-6707f6d2df51","physical_cards":[],"virtual_cards":[],"top_up_operations":[],"purchase_operations":[],"transfer_operations":[],"cash_withdrawal_operations":[]}],"credit_card_accounts":[]},{"user_id":"43e84378-5541-4dd5-a4ae-3fbb09e23f06","deposit_accounts":[],"savings_accounts":[{"account_id":"09057657-4b53-4c29-b1ba-d6898d66ac3a","physical_cards":[],"virtual_cards":[],"top_up_operations":[],"purchase_operations":[],"transfer_operations":[],"cash_withdrawal_operations":[]}],"debit_card_accounts":[{"account_id":"782bfb38-f1fa-4cc0-8e21-5709c54ecf13","physical_cards":[],"virtual_cards":[],"top_up_operations":[],"purchase_operations":[],"transfer_operations":[],"cash_withdrawal_operations":[]}],"credit_card_accounts":[]},{"user_id":"d64f95ff-4daf-4d89-9320-fbbc28ce1754","deposit_accounts":[],"savings_accounts":[{"account_id":"37b91eb6-9d37-4b39-94fd-2a1f28c9a020","physical_cards":[],"virtual_cards":[],"top_up_operations":[],"purchase_operations":[],"transfer_operations":[],"cash_withdrawal_operations":[]}],"debit_card_accounts":[{"account_id":"b7aa7380-49e6-43a0-b5a0-b31b5e71c645","physical_cards":[],"virtual_cards":[],"top_up_operations":[],"purchase_operations":[],"transfer_operations":[],"cash_withdrawal_operations":[]}],"credit_card_accounts":[]},{"user_id":"e9cd6331-f03c-4fc4-94b5-0f42459ff116","deposit_accounts":[],"savings_accounts":[{"account_id":"91d4dd42-c3b1-4634-8804-b717d6f665b1","physical_cards":[],"virtual_cards":[],"top_up_operations":[],"purchase_operations":[],"transfer_operations":[],"cash_withdrawal_operations":[]}],"debit_card_accounts":[{"account_id":"1a29914f-8393-4f4a-b139-07a24b807e43","physical_cards":[],"virtual_cards":[],"top_up_operations":[],"purchase_operations":[],"transfer_operations":[],"cash_withdrawal_operations":[]}],"credit_card_accounts":[]},{"user_id":"78093b7d-b87c-45a4-9c28-fa1fd6ca6caa","deposit_accounts":[],"savings_accounts":[{"account_id":"d3444da4-bf45-47f1-bc8b-e4344c56b200","physical_cards":[],"virtual_cards":[],"top_up_operations":[],"purchase_operations":[],"transfer_operations":[],"cash_withdrawal_operations":[]}],"debit_card_accounts":[{"account_id":"cf423d7d-a4e4-4e8f-906a-1a684fdf6517","physical_cards":[],"virtual_cards":[],"top_up_operations":[],"purchase_operations":[],"transfer_operations":[],"cash_withdrawal_operations":[]}],"credit_card_accounts":[]},{"user_id":"4add7c0a-4183-40cb-bf54-b8d0e45dfaf1","deposit_accounts":[],"savings_accounts":[{"account_id":"20b8e7e4-778f-4028-be8e-e975a6c2c157","physical_cards":[],"virtual_cards":[],"top_up_operations":[],"purchase_operations":[],"transfer_operations":[],"cash_withdrawal_operations":[]}],"debit_card_accounts":[{"account_id":"12d28743-ab64-45c4-b8f8-842b0d209afc","physical_cards":[],"virtual_cards":[],"top_up_operations":[],"purchase_operations":[],"transfer_operations":[],"cash_withdrawal_operations":[]}],"credit_card_accounts":[]},{"user_id":"02e04701-8cac-477d-bdae-2f10bbbf7ee8","deposit_accounts":[],"savings_accounts":[{"account_id":"b6744d10-4aad-4825-bdae-218b885f7394","physical_cards":[],"virtual_cards":[],"top_up_operations":[],"purchase_operations":[],"transfer_operations":[],"cash_withdrawal_operations":[]}],"debit_card_accounts":[{"account_id":"7feac0da-419d-475f-9c9a-129eb8d38161","physical_cards":[],"virtual_cards":[],"top_up_operations":[],"purchase_operations":[],"transfer_operations":[],"cash_withdrawal_operations":[]}],"credit_card_accounts":[]},{"user_id":"6294a8a3-474b-4b18-9fb1-19e4e281b3ab","deposit_accounts":[],"savings_accounts":[{"account_id":"cc94b871-4ea5-422f-a3c5-129e2b09fd3f","physical_cards":[],"virtual_cards":[],"top_up_operations":[],"purchase_operations":[],"transfer_operations":[],"cash_withdrawal_operations":[]}],"debit_card_accounts":[{"account_id":"49d57088-e792-41fc-a19b-b8d52869bfaa","physical_cards":[],"virtual_cards":[],"top_up_operations":[],"purchase_operations":[],"transfer_operations":[],"cash_withdrawal_operations":[]}],"credit_card_accounts":[]},{"user_id":"3214f58a-f9f0-4d8e-86ff-5c4cc46375c4","deposit_accounts":[],"savings_accounts":[{"account_id":"fd108978-58c4-4cc2-bcc8-b220668f6ad4","physical_cards":[],"virtual_cards":[],"top_up_operations":[],"purchase_operations":[],"transfer_operations":[],"cash_withdrawal_operations":[]}],"debit_card_accounts":[{"account_id":"7a2feceb-c401-4b4a-aadc-6fd9f643687b","physical_cards":[],"virtual_cards":[],"top_up_operations":[],"purchase_operations":[],"transfer_operations":[],"cash_withdrawal_operations":[]}],"credit_card_accounts":[]},{"user_id":"03e1efe8-ff21-4b34-b955-d7e041fb629f","deposit_accounts":[],"savings_accounts":[{"account_id":"8fa5a086-5abc-48f5-a5d0-9e9c0f918602","physical_cards":[],"virtual_cards":[],"top_up_operations":[],"purchase_operations":[],"transfer_operations":[],"cash_withdrawal_operations":[]}],"debit_card_accounts":[{"account_id":"041c273e-797c-44de-8db5-4dfebca48d53","physical_cards":[],"virtual_cards":[],"top_up_operations":[],"purchase_operations":[],"transfer_operations":[],"cash_withdrawal_operations":[]}],"credit_card_accounts":[]},{"user_id":"219c0e5d-bdae-44a4-b8e1-15a88b77ee93","deposit_accounts":[],"savings_accounts":[{"account_id":"3a345e10-51be-43cd-a97b-78dec5ef957d","physical_cards":[],"virtual_cards":[],"top_up_operations":[],"purchase_operations":[],"transfer_operations":[],"cash_withdrawal_operations":[]}],"debit_card_accounts":[{"account_id":"e04c0d1e-69cc-4531-9a56-d963445dcf38","physical_cards":[],"virtual_cards":[],"top_up_operations":[],"purchase_operations":[],"transfer_operations":[],"cash_withdrawal_operations":[]}],"credit_card_accounts":[]},{"user_id":"1f8c2500-8f1e-4c1b-9190-1b59e00a09c1","deposit_accounts":[],"savings_accounts":[{"account_id":"c35ae154-4486-4ec1-a070-3faa9911df73","physical_cards":[],"virtual_cards":[],"top_up_operations":[],"purchase_operations":[],"transfer_operations":[],"cash_withdrawal_operations":[]}],"debit_card_accounts":[{"account_id":"f5a50061-33fe-4021-8e66-52ab67f60814","physical_cards":[],"virtual_cards":[],"top_up_operations":[],"purchase_operations":[],"transfer_operations":[],"cash_withdrawal_operations":[]}],"credit_card_accounts":[]},{"user_id":"b36e3825-14f7-40d1-94c3-497c00803cdb","deposit_accounts":[],"savings_accounts":[{"account_id":"8d6c5549-a3b5-4f19-bfa6-dacd1489e3b1","physical_cards":[],"virtual_cards":[],"top_up_operations":[],"purchase_operations":[],"transfer_operations":[],"cash_withdrawal_operations":[]}],"debit_card_accounts":[{"account_id":"a5c95f0d-63bd-498e-891b-19013be11698","physical_cards":[],"virtual_cards":[],"top_up_operations":[],"purchase_operations":[],"transfer_operations":[],"cash_withdrawal_operations":[]}],"credit_card_accounts":[]},{"user_id":"81692fd9-6446-44e3-9970-0371719569f1","deposit_accounts":[],"savings_accounts":[{"account_id":"a2617b36-a67c-4e03-95fa-892f3e813cd7","physical_cards":[],"virtual_cards":[],"top_up_operations":[],"purchase_operations":[],"transfer_operations":[],"cash_withdrawal_operations":[]}],"debit_card_accounts":[{"account_id":"b7ecb89c-2e28-427d-85f8-5d4af121500d","physical_cards":[],"virtual_cards":[],"top_up_operations":[],"purchase_operations":[],"transfer_operations":[],"cash_withdrawal_operations":[]}],"credit_card_accounts":[]},{"user_id":"62e3fd2e-3e38-4178-99bd-03294db00cec","deposit_accounts":[],"savings_accounts":[{"account_id":"f82677c0-20c3-4c6d-9321-e7884514017a","physical_cards":[],"virtual_cards":[],"top_up_operations":[],"purchase_operations":[],"transfer_operations":[],"cash_withdrawal_operations":[]}],"debit_card_accounts":[{"account_id":"2fd048a9-dc00-4a8a-9f0d-6bc972ed7059","physical_cards":[],"virtual_cards":[],"top_up_operations":[],"purchase_operations":[],"transfer_operations":[],"cash_withdrawal_operations":[]}],"credit_card_accounts":[]},{"user_id":"4c4f0c1e-b167-4a0b-9932-0d481a5f546a","deposit_accounts":[],"savings_accounts":[{"account_id":"fba54620-d482-43ec-bad7-3927476135fe","physical_cards":[],"virtual_cards":[],"top_up_operations":[],"purchase_operations":[],"transfer_operations":[],"cash_withdrawal_operations":[]}],"debit_card_accounts":[{"account_id":"fc0ec968-3175-41ed-bfba-1a3f4e4c5510","physical_cards":[],"virtual_cards":[],"top_up_operations":[],"purchase_operations":[],"transfer_operations":[],"cash_withdrawal_operations":[]}],"credit_card_accounts":[]},{"user_id":"5eb4c121-5e4e-4d6d-bf4c-eb7af0da40b3","deposit_accounts":[],"savings_accounts":[{"account_id":"f30d02a4-696a-4975-b4ef-3fcd19b842a6","physical_cards":[],"virtual_cards":[],"top_up_operations":[],"purchase_operations":[],"transfer_operations":[],"cash_withdrawal_operations":[]}],"debit_card_accounts":[{"account_id":"6b0fe084-1b81-4ae2-a55b-a25ba20dc8de","physical_cards":[],"virtual_cards":[],"top_up_operations":[],"purchase_operations":[],"transfer_operations":[],"cash_withdrawal_operations":[]}],"credit_card_accounts":[]},{"user_id":"18259e6b-5e9e-45e6-9368-ecd445381096","deposit_accounts":[],"savings_accounts":[{"account_id":"b3832814-ce13-4906-b89e-1001c2a1d35f","physical_cards":[],"virtual_cards":[],"top_up_operations":[],"purchase_operations":[],"transfer_operations":[],"cash_withdrawal_operations":[]}],"debit_card_accounts":[{"account_id":"80b9f855-144e-4a5a-87ba-4c3a818b001f","physical_cards":[],"virtual_cards":[],"top_up_operations":[],"purchase_operations":[],"transfer_operations":[],"cash_withdrawal_operations":[]}],"credit_card_accounts":[]},{"user_id":"0e72a1fb-ebcc-4b16-a266-5f6c6b695af6","deposit_accounts":[],"savings_accounts":[{"account_id":"d2fc0ef0-eec3-418c-a64c-89769660a942","physical_cards":[],"virtual_cards":[],"top_up_operations":[],"purchase_operations":[],"transfer_operations":[],"cash_withdrawal_operations":[]}],"debit_card_accounts":[{"account_id":"91aa128f-cef1-4fda-9bea-01561656d537","physical_cards":[],"virtual_cards":[],"top_up_operations":[],"purchase_operations":[],"transfer_operations":[],"cash_withdrawal_operations":[]}],"credit_card_accounts":[]},{"user_id":"2f9b5d75-dc4a-4a58-9696-c122e4e02a90","deposit_accounts":[],"savings_accounts":[{"account_id":"748121bc-ffe5-48c3-a46b-c18589341c08","physical_cards":[],"virtual_cards":[],"top_up_operations":[],"purchase_operations":[],"transfer_operations":[],"cash_withdrawal_operations":[]}],"debit_card_accounts":[{"account_id":"e028e9a2-190e-4ee3-ab07-fea09e3cdf53","physical_cards":[],"virtual_cards":[],"top_up_operations":[],"purchase_operations":[],"transfer_operations":[],"cash_withdrawal_operations":[]}],"credit_card_accounts":[]},{"user_id":"df3584be-590e-41da-9ba9-416043d2845e","deposit_accounts":[],"savings_accounts":[{"account_id":"cf47837b-22b4-4aa3-a856-1a7f8aca4f3c","physical_cards":[],"virtual_cards":[],"top_up_operations":[],"purchase_operations":[],"transfer_operations":[],"cash_withdrawal_operations":[]}],"debit_card_accounts":[{"account_id":"3f44d854-4bc4-4393-bc5b-3fb224475a6f","physical_cards":[],"virtual_cards":[],"top_up_operations":[],"purchase_operations":[],"transfer_operations":[],"cash_withdrawal_operations":[]}],"credit_card_accounts":[]},{"user_id":"1bb5ad5e-e2e5-42ca-81ee-ba0c2efb9e4d","deposit_accounts":[],"savings_accounts":[{"account_id":"fce3fc74-2885-41be-ba1a-82cff895f780","physical_cards":[],"virtual_cards":[],"top_up_operations":[],"purchase_operations":[],"transfer_operations":[],"cash_withdrawal_operations":[]}],"debit_card_accounts":[{"account_id":"7f5d5269-99d8-43f5-9f34-c87f5dc12c67","physical_cards":[],"virtual_cards":[],"top_up_operations":[],"purchase_operations":[],"transfer_operations":[],"cash_withdrawal_operations":[]}],"credit_card_accounts":[]},{"user_id":"4cc053e0-a1c8-481e-a111-772dcffb8d75","deposit_accounts":[],"savings_accounts":[{"account_id":"56cf7945-a33c-4adb-b925-d649b170bb67","physical_cards":[],"virtual_cards":[],"top_up_operations":[],"purchase_operations":[],"transfer_operations":[],"cash_withdrawal_operations":[]}],"debit_card_accounts":[{"account_id":"e08b455c-91cc-4d39-9516-768b282aa86c","physical_cards":[],"virtual_cards":[],"top_up_operations":[],"purchase_operations":[],"transfer_operations":[],"cash_withdrawal_operations":[]}],"credit_card_accounts":[]},{"user_id":"a3a4fa9c-fce1-4635-af71-bc79dc49daba","deposit_accounts":[],"savings_accounts":[{"account_id":"be11333e-414d-49a3-8163-d41fb84402cf","physical_cards":[],"virtual_cards":[],"top_up_operations":[],"purchase_operations":[],"transfer_operations":[],"cash_withdrawal_operations":[]}],"debit_card_accounts":[{"account_id":"ee0bc6e0-eca1-4268-811d-c57cb993b51b","physical_cards":[],"virtual_cards":[],"top_up_operations":[],"purchase_operations":[],"transfer_operations":[],"cash_withdrawal_operations":[]}],"credit_card_accounts":[]},{"user_id":"34c2c611-cc25-4283-b006-870531688906","deposit_accounts":[],"savings_accounts":[{"account_id":"fca581eb-f67e-422e-a363-c827b116f1f0","physical_cards":[],"virtual_cards":[],"top_up_operations":[],"purchase_operations":[],"transfer_operations":[],"cash_withdrawal_operations":[]}],"debit_card_accounts":[{"account_id":"8e080b51-a9c1-4aa4-a822-0dba1e6d9729","physical_cards":[],"virtual_cards":[],"top_up_operations":[],"purchase_operations":[],"transfer_operations":[],"cash_withdrawal_operations":[]}],"credit_card_accounts":[]},{"user_id":"b6541651-c86f-4096-aa41-3c6ad176004e","deposit_accounts":[],"savings_accounts":[{"account_id":"b9a8ca9b-4be2-4f93-8ee3-7ad1778fb176","physical_cards":[],"virtual_cards":[],"top_up_operations":[],"purchase_operations":[],"transfer_operations":[],"cash_withdrawal_operations":[]}],"debit_card_accounts":[{"account_id":"999e4aad-b3ba-418f-9b25-20680a91c68e","physical_cards":[],"virtual_cards":[],"top_up_operations":[],"purchase_operations":[],"transfer_operations":[],"cash_withdrawal_operations":[]}],"credit_card_accounts":[]},{"user_id":"5dd154cc-2cb8-4f46-b9f7-79c474d1d7f6","deposit_accounts":[],"savings_accounts":[{"account_id":"14aea268-673d-4c97-8de8-cc63f27aebc0","physical_cards":[],"virtual_cards":[],"top_up_operations":[],"purchase_operations":[],"transfer_operations":[],"cash_withdrawal_operations":[]}],"debit_card_accounts":[{"account_id":"b47dd938-bdcf-40cf-ad5c-303fd5cb012c","physical_cards":[],"virtual_cards":[],"top_up_operations":[],"purchase_operations":[],"transfer_operations":[],"cash_withdrawal_operations":[]}],"credit_card_accounts":[]},{"user_id":"750098fb-fcb4-41aa-b5e4-c8af90e1f886","deposit_accounts":[],"savings_accounts":[{"account_id":"a8b4a1bb-403b-4838-96da-962e0220ccf5","physical_cards":[],"virtual_cards":[],"top_up_operations":[],"purchase_operations":[],"transfer_operations":[],"cash_withdrawal_operations":[]}],"debit_card_accounts":[{"account_id":"383ab900-ea36-49ae-9000-bf2b41f88dc6","physical_cards":[],"virtual_cards":[],"top_up_operations":[],"purchase_operations":[],"transfer_operations":[],"cash_withdrawal_operations":[]}],"credit_card_accounts":[]},{"user_id":"3b496e32-4bb5-45ae-b2cd-c89129351f77","deposit_accounts":[],"savings_accounts":[{"account_id":"eb1d7b69-45be-4267-a0d3-98d829807485","physical_cards":[],"virtual_cards":[],"top_up_operations":[],"purchase_operations":[],"transfer_operations":[],"cash_withdrawal_operations":[]}],"debit_card_accounts":[{"account_id":"95ee2985-ffbd-4689-90e8-6cd36c9a299f","physical_cards":[],"virtual_cards":[],"top_up_operations":[],"purchase_operations":[],"transfer_operations":[],"cash_withdrawal_operations":[]}],"credit_card_accounts":[]},{"user_id":"6f988080-cbc4-42e0-b9e1-bf0da3b27745","deposit_accounts":[],"savings_accounts":[{"account_id":"a952e59c-aafe-4997-ba98-0c23e973c684","physical_cards":[],"virtual_cards":[],"top_up_operations":[],"purchase_operations":[],"transfer_operations":[],"cash_withdrawal_operations":[]}],"debit_card_accounts":[{"account_id":"04ca93bc-87bf-4e16-bfb0-8f11419c486f","physical_cards":[],"virtual_cards":[],"top_up_operations":[],"purchase_operations":[],"transfer_operations":[],"cash_withdrawal_operations":[]}],"credit_card_accounts":[]},{"user_id":"4ad9c3a4-5e39-4c9f-bc20-379cd019b0bf","deposit_accounts":[],"savings_accounts":[{"account_id":"6a3128b0-8dfd-42e6-8a47-d5d22ac75256","physical_cards":[],"virtual_cards":[],"top_up_operations":[],"purchase_operations":[],"transfer_operations":[],"cash_withdrawal_operations":[]}],"debit_card_accounts":[{"account_id":"fc33699b-b1cd-4434-a499-0fec3faf1896","physical_cards":[],"virtual_cards":[],"top_up_operations":[],"purchase_operations":[],"transfer_operations":[],"cash_withdrawal_operations":[]}],"credit_card_accounts":[]},{"user_id":"63aa34ee-8a95-42bb-9f43-2730a80660c2","deposit_accounts":[],"savings_accounts":[{"account_id":"a117c229-189a-4458-9e79-eb954f0bd8a3","physical_cards":[],"virtual_cards":[],"top_up_operations":[],"purchase_operations":[],"transfer_operations":[],"cash_withdrawal_operations":[]}],"debit_card_accounts":[{"account_id":"0f04b9f8-4c93-4f84-9ffa-98cf2d7e9856","physical_cards":[],"virtual_cards":[],"top_up_operations":[],"purchase_operations":[],"transfer_operations":[],"cash_withdrawal_operations":[]}],"credit_card_accounts":[]},{"user_id":"cd2e46d8-278d-4675-8e48-ec90bdd18d5d","deposit_accounts":[],"savings_accounts":[{"account_id":"e09d0a4f-79ad-42c3-93ae-93e1adfe281d","physical_cards":[],"virtual_cards":[],"top_up_operations":[],"purchase_operations":[],"transfer_operations":[],"cash_withdrawal_operations":[]}],"debit_card_accounts":[{"account_id":"fc50499d-3999-4f5f-ad76-fda96718d5ec","physical_cards":[],"virtual_cards":[],"top_up_operations":[],"purchase_operations":[],"transfer_operations":[],"cash_withdrawal_operations":[]}],"credit_card_accounts":[]},{"user_id":"82356d0b-0648-4a43-bc97-2f26568ae498","deposit_accounts":[],"savings_accounts":[{"account_id":"9a54aa88-c8ea-4bb3-84ed-f77a975cfd61","physical_cards":[],"virtual_cards":[],"top_up_operations":[],"purchase_operations":[],"transfer_operations":[],"cash_withdrawal_operations":[]}],"debit_card_accounts":[{"account_id":"5913f9ac-a63c-450f-88fd-ff406956d3c2","physical_cards":[],"virtual_cards":[],"top_up_operations":[],"purchase_operations":[],"transfer_operations":[],"cash_withdrawal_operations":[]}],"credit_card_accounts":[]},{"user_id":"f828310d-d245-4020-957a-65b870d39521","deposit_accounts":[],"savings_accounts":[{"account_id":"e0b28988-7437-4929-9eb4-07b49161d306","physical_cards":[],"virtual_cards":[],"top_up_operations":[],"purchase_operations":[],"transfer_operations":[],"cash_withdrawal_operations":[]}],"debit_card_accounts":[{"account_id":"ba081d7a-0731-4a04-915e-59dc78ac6294","physical_cards":[],"virtual_cards":[],"top_up_operations":[],"purchase_operations":[],"transfer_operations":[],"cash_withdrawal_operations":[]}],"credit_card_accounts":[]},{"user_id":"3c95bca7-a60d-4feb-bc6f-9baa6051dec9","deposit_accounts":[],"savings_accounts":[{"account_id":"8644beb6-b3d6-4dff-8235-409d66cab720","physical_cards":[],"virtual_cards":[],"top_up_operations":[],"purchase_operations":[],"transfer_operations":[],"cash_withdrawal_operations":[]}],"debit_card_accounts":[{"account_id":"0cd1650b-7046-424a-b5e8-3fe4dd333001","physical_cards":[],"virtual_cards":[],"top_up_operations":[],"purchase_operations":[],"transfer_operations":[],"cash_withdrawal_operations":[]}],"credit_card_accounts":[]},{"user_id":"31b9d0e4-661d-433e-853a-b7371ab9cb91","deposit_accounts":[],"savings_accounts":[{"account_id":"1f2c5b3b-f191-46f2-a8e2-f08a56ee2e61","physical_cards":[],"virtual_cards":[],"top_up_operations":[],"purchase_operations":[],"transfer_operations":[],"cash_withdrawal_operations":[]}],"debit_card_accounts":[{"account_id":"ac47775b-a686-40b7-a972-787ed4bc9e8c","physical_cards":[],"virtual_cards":[],"top_up_operations":[],"purchase_operations":[],"transfer_operations":[],"cash_withdrawal_operations":[]}],"credit_card_accounts":[]},{"user_id":"38a847c1-5b1a-45d6-90f1-fe28f76b6d38","deposit_accounts":[],"savings_accounts":[{"account_id":"dcfdb29f-e591-4967-be25-f8c56436f363","physical_cards":[],"virtual_cards":[],"top_up_operations":[],"purchase_operations":[],"transfer_operations":[],"cash_withdrawal_operations":[]}],"debit_card_accounts":[{"account_id":"245866ac-7972-4faa-86c1-5ed94de1d45e","physical_cards":[],"virtual_cards":[],"top_up_operations":[],"purchase_operations":[],"transfer_operations":[],"cash_withdrawal_operations":[]}],"credit_card_accounts":[]},{"user_id":"6cc48d52-0a14-4c23-978e-b0e5a53e47d4","deposit_accounts":[],"savings_accounts":[{"account_id":"b1c73983-6d9a-46c0-a5f3-e14a0ca4d792","physical_cards":[],"virtual_cards":[],"top_up_operations":[],"purchase_operations":[],"transfer_operations":[],"cash_withdrawal_operations":[]}],"debit_card_accounts":[{"account_id":"4fa8213a-7974-4a42-be36-7fe6a2b20aba","physical_cards":[],"virtual_cards":[],"top_up_operations":[],"purchase_operations":[],"transfer_operations":[],"cash_withdrawal_operations":[]}],"credit_card_accounts":[]},{"user_id":"cff02dca-5e5c-4c84-9283-cc409643e5dc","deposit_accounts":[],"savings_accounts":[{"account_id":"1f79b508-afc5-47ab-a439-111131673040","physical_cards":[],"virtual_cards":[],"top_up_operations":[],"purchase_operations":[],"transfer_operations":[],"cash_withdrawal_operations":[]}],"debit_card_accounts":[{"account_id":"da9b767a-bc2c-4fb9-b40e-00e6325f3181","physical_cards":[],"virtual_cards":[],"top_up_operations":[],"purchase_operations":[],"transfer_operations":[],"cash_withdrawal_operations":[]}],"credit_card_accounts":[]},{"user_id":"9cadce8c-b906-42dd-ac9f-05c0ada81145","deposit_accounts":[],"savings_accounts":[{"account_id":"68de60e1-fd95-4414-8ea5-3b986990c85d","physical_cards":[],"virtual_cards":[],"top_up_operations":[],"purchase_operations":[],"transfer_operations":[],"cash_withdrawal_operations":[]}],"debit_card_accounts":[{"account_id":"c0fa2337-6dcd-4693-b042-2e56a7a71cd6","physical_cards":[],"virtual_cards":[],"top_up_operations":[],"purchase_operations":[],"transfer_operations":[],"cash_withdrawal_operations":[]}],"credit_card_accounts":[]},{"user_id":"25d2b9a2-1d85-4a76-b181-b7e4d9bfd461","deposit_accounts":[],"savings_accounts":[{"account_id":"52212555-5439-4162-891d-3af6bb11a7a9","physical_cards":[],"virtual_cards":[],"top_up_operations":[],"purchase_operations":[],"transfer_operations":[],"cash_withdrawal_operations":[]}],"debit_card_accounts":[{"account_id":"66bc5b34-2b24-4401-91b4-3b3a88800289","physical_cards":[],"virtual_cards":[],"top_up_operations":[],"purchase_operations":[],"transfer_operations":[],"cash_withdrawal_operations":[]}],"credit_card_accounts":[]},{"user_id":"ec5fad5f-8da7-4738-9ba3-fde0a547b69e","deposit_accounts":[],"savings_accounts":[{"account_id":"5376a81f-6add-4109-8b99-656e5ea7e869","physical_cards":[],"virtual_cards":[],"top_up_operations":[],"purchase_operations":[],"transfer_operations":[],"cash_withdrawal_operations":[]}],"debit_card_accounts":[{"account_id":"606b1b0c-6666-4f56-98de-158c0c865b44","physical_cards":[],"virtual_cards":[],"top_up_operations":[],"purchase_operations":[],"transfer_operations":[],"cash_withdrawal_operations":[]}],"credit_card_accounts":[]},{"user_id":"ce3c7dee-619b-4376-9f87-43280bc5603a","deposit_accounts":[],"savings_accounts":[{"account_id":"93dbfc5a-18c6-4662-ae9c-775606c37ccd","physical_cards":[],"virtual_cards":[],"top_up_operations":[],"purchase_operations":[],"transfer_operations":[],"cash_withdrawal_operations":[]}],"debit_card_accounts":[{"account_id":"969c8722-f77c-49b2-953f-9c10251b596a","physical_cards":[],"virtual_cards":[],"top_up_operations":[],"purchase_operations":[],"transfer_operations":[],"cash_withdrawal_operations":[]}],"credit_card_accounts":[]},{"user_id":"2f2654bd-9850-43e6-b8a2-74ce0979aade","deposit_accounts":[],"savings_accounts":[{"account_id":"e9fbb081-f211-4113-9eb0-b4d0c6d074d1","physical_cards":[],"virtual_cards":[],"top_up_operations":[],"purchase_operations":[],"transfer_operations":[],"cash_withdrawal_operations":[]}],"debit_card_accounts":[{"account_id":"8e3cd948-2168-4c89-b40a-6fb56189026f","physical_cards":[],"virtual_cards":[],"top_up_operations":[],"purchase_operations":[],"transfer_operations":[],"cash_withdrawal_operations":[]}],"credit_card_accounts":[]},{"user_id":"a1999676-1a96-40bf-9ae0-159034ceb03b","deposit_accounts":[],"savings_accounts":[{"account_id":"38eb15fc-cba0-4a35-9a55-4d8686be2898","physical_cards":[],"virtual_cards":[],"top_up_operations":[],"purchase_operations":[],"transfer_operations":[],"cash_withdrawal_operations":[]}],"debit_card_accounts":[{"account_id":"ca775334-d1e7-4f4e-acf6-6f35a1de28ae","physical_cards":[],"virtual_cards":[],"top_up_operations":[],"purchase_operations":[],"transfer_operations":[],"cash_withdrawal_operations":[]}],"credit_card_accounts":[]},{"user_id":"ea49be8f-aa56-4b7f-8b66-9ea46167c776","deposit_accounts":[],"savings_accounts":[{"account_id":"795876ea-6512-4f8e-b92e-88423f9b0a09","physical_cards":[],"virtual_cards":[],"top_up_operations":[],"purchase_operations":[],"transfer_operations":[],"cash_withdrawal_operations":[]}],"debit_card_accounts":[{"account_id":"3f88b678-3789-4200-bdb7-b9f59a9327eb","physical_cards":[],"virtual_cards":[],"top_up_operations":[],"purchase_operations":[],"transfer_operations":[],"cash_withdrawal_operations":[]}],"credit_card_accounts":[]},{"user_id":"65c8ee5d-0185-4a96-8fd6-f86a24424df0","deposit_accounts":[],"savings_accounts":[{"account_id":"75cd9408-c1d2-42d6-85ad-f90511000fc7","physical_cards":[],"virtual_cards":[],"top_up_operations":[],"purchase_operations":[],"transfer_operations":[],"cash_withdrawal_operations":[]}],"debit_card_accounts":[{"account_id":"3edfebd3-f924-4963-b097-8641006d0588","physical_cards":[],"virtual_cards":[],"top_up_operations":[],"purchase_operations":[],"transfer_operations":[],"cash_withdrawal_operations":[]}],"credit_card_accounts":[]},{"user_id":"8586ecee-d983-44e1-ab6f-6e9c7a293e78","deposit_accounts":[],"savings_accounts":[{"account_id":"e16f49a3-0fcb-4c06-9283-87e60e77fcab","physical_cards":[],"virtual_cards":[],"top_up_operations":[],"purchase_operations":[],"transfer_operations":[],"cash_withdrawal_operations":[]}],"debit_card_accounts":[{"account_id":"b0ce98c6-960a-47eb-95a2-7be59b1d0fd8","physical_cards":[],"virtual_cards":[],"top_up_operations":[],"purchase_operations":[],"transfer_operations":[],"cash_withdrawal_operations":[]}],"credit_card_accounts":[]},{"user_id":"13c9ef9c-6dae-450d-9e77-80e721ae9d83","deposit_accounts":[],"savings_accounts":[{"account_id":"c6ee52cc-e8d3-44d3-8580-45ba11708623","physical_cards":[],"virtual_cards":[],"top_up_operations":[],"purchase_operations":[],"transfer_operations":[],"cash_withdrawal_operations":[]}],"debit_card_accounts":[{"account_id":"8f4512ab-08b1-4929-a33c-f89fad860117","physical_cards":[],"virtual_cards":[],"top_up_operations":[],"purchase_operations":[],"transfer_operations":[],"cash_withdrawal_operations":[]}],"credit_card_accounts":[]},{"user_id":"cb0462d8-cb5a-48ee-85a1-55c51b7962ad","deposit_accounts":[],"savings_accounts":[{"account_id":"1e3d8d4e-51a1-466a-993b-7ed6feecae85","physical_cards":[],"virtual_cards":[],"top_up_operations":[],"purchase_operations":[],"transfer_operations":[],"cash_withdrawal_operations":[]}],"debit_card_accounts":[{"account_id":"16c5c376-9d7a-4c8d-9d8c-b87d9dd1e1de","physical_cards":[],"virtual_cards":[],"top_up_operations":[],"purchase_operations":[],"transfer_operations":[],"cash_withdrawal_operations":[]}],"credit_card_accounts":[]},{"user_id":"bff95f9f-7323-4814-96c3-4ccadb5cfd45","deposit_accounts":[],"savings_accounts":[{"account_id":"91a18832-56e8-40bb-a3f3-2894aaf36c7a","physical_cards":[],"virtual_cards":[],"top_up_operations":[],"purchase_operations":[],"transfer_operations":[],"cash_withdrawal_operations":[]}],"debit_card_accounts":[{"account_id":"31a10e32-0025-4089-a6b6-352ae9f0b162","physical_cards":[],"virtual_cards":[],"top_up_operations":[],"purchase_operations":[],"transfer_operations":[],"cash_withdrawal_operations":[]}],"credit_card_accounts":[]},{"user_id":"77832f9e-beb3-468a-8c95-bb8a0d52c90f","deposit_accounts":[],"savings_accounts":[{"account_id":"0924ed58-151d-46b4-a3dd-45c6c24bc4c9","physical_cards":[],"virtual_cards":[],"top_up_operations":[],"purchase_operations":[],"transfer_operations":[],"cash_withdrawal_operations":[]}],"debit_card_accounts":[{"account_id":"043187ec-1af5-4c73-b6bb-4f0890b89519","physical_cards":[],"virtual_cards":[],"top_up_operations":[],"purchase_operations":[],"transfer_operations":[],"cash_withdrawal_operations":[]}],"credit_card_accounts":[]},{"user_id":"0c8bbffb-e83b-4df4-8cbe-b9a0ea86c635","deposit_accounts":[],"savings_accounts":[{"account_id":"b908442d-baec-440f-8d29-4231633de435","physical_cards":[],"virtual_cards":[],"top_up_operations":[],"purchase_operations":[],"transfer_operations":[],"cash_withdrawal_operations":[]}],"debit_card_accounts":[{"account_id":"e140e823-5cbb-471a-be5c-ec95e7b2e48a","physical_cards":[],"virtual_cards":[],"top_up_operations":[],"purchase_operations":[],"transfer_operations":[],"cash_withdrawal_operations":[]}],"credit_card_accounts":[]},{"user_id":"66cbb712-40df-4fac-b0e8-0217c305a23c","deposit_accounts":[],"savings_accounts":[{"account_id":"51e98f90-0f04-44eb-8e00-a0a1dde8ac96","physical_cards":[],"virtual_cards":[],"top_up_operations":[],"purchase_operations":[],"transfer_operations":[],"cash_withdrawal_operations":[]}],"debit_card_accounts":[{"account_id":"51b8d596-67e6-4587-b064-1c66b229b742","physical_cards":[],"virtual_cards":[],"top_up_operations":[],"purchase_operations":[],"transfer_operations":[],"cash_withdrawal_operations":[]}],"credit_card_accounts":[]},{"user_id":"a406dc69-14b1-467b-8eae-6df076cf7fe8","deposit_accounts":[],"savings_accounts":[{"account_id":"6c3d4b82-b7e1-4709-b084-531b8aa65c17","physical_cards":[],"virtual_cards":[],"top_up_operations":[],"purchase_operations":[],"transfer_operations":[],"cash_withdrawal_operations":[]}],"debit_card_accounts":[{"account_id":"95a30d77-e423-4fae-8784-dc64bb6c0f0c","physical_cards":[],"virtual_cards":[],"top_up_operations":[],"purchase_operations":[],"transfer_operations":[],"cash_withdrawal_operations":[]}],"credit_card_accounts":[]},{"user_id":"05afc3cc-afd5-478f-8284-860aa5c66c93","deposit_accounts":[],"savings_accounts":[{"account_id":"1784a1c8-5548-45d0-a911-10d74f5b7653","physical_cards":[],"virtual_cards":[],"top_up_operations":[],"purchase_operations":[],"transfer_operations":[],"cash_withdrawal_operations":[]}],"debit_card_accounts":[{"account_id":"ff8ecd48-7177-4900-abc8-660d8633c284","physical_cards":[],"virtual_cards":[],"top_up_operations":[],"purchase_operations":[],"transfer_operations":[],"cash_withdrawal_operations":[]}],"credit_card_accounts":[]},{"user_id":"4f67465a-c30a-4b76-9a5c-d7b19c376a2a","deposit_accounts":[],"savings_accounts":[{"account_id":"342a4007-fac7-4302-9440-ff967ec37229","physical_cards":[],"virtual_cards":[],"top_up_operations":[],"purchase_operations":[],"transfer_operations":[],"cash_withdrawal_operations":[]}],"debit_card_accounts":[{"account_id":"f8b40f7f-4278-4555-a2d6-67884f3d0a0a","physical_cards":[],"virtual_cards":[],"top_up_operations":[],"purchase_operations":[],"transfer_operations":[],"cash_withdrawal_operations":[]}],"credit_card_accounts":[]},{"user_id":"02f5be7a-d025-434d-b414-00181132d7bb","deposit_accounts":[],"savings_accounts":[{"account_id":"6479f72f-1ace-4a02-bdf7-8f4b04cd4fca","physical_cards":[],"virtual_cards":[],"top_up_operations":[],"purchase_operations":[],"transfer_operations":[],"cash_withdrawal_operations":[]}],"debit_card_accounts":[{"account_id":"e2c272b7-1b83-4987-b5cb-7d7b4cc34a25","physical_cards":[],"virtual_cards":[],"top_up_operations":[],"purchase_operations":[],"transfer_operations":[],"cash_withdrawal_operations":[]}],"credit_card_accounts":[]},{"user_id":"2272ae01-9b35-435a-b715-296a82af7380","deposit_accounts":[],"savings_accounts":[{"account_id":"bbe81e5f-2b4a-4942-b7df-bf11d79d463c","physical_cards":[],"virtual_cards":[],"top_up_operations":[],"purchase_operations":[],"transfer_operations":[],"cash_withdrawal_operations":[]}],"debit_card_accounts":[{"account_id":"cabb97d6-c467-4215-9b66-8bd4a018daf6","physical_cards":[],"virtual_cards":[],"top_up_operations":[],"purchase_operations":[],"transfer_operations":[],"cash_withdrawal_operations":[]}],"credit_card_accounts":[]}]}